{
  "forward_walk": {
    "steps": 1000.0,
    "survival_rate": 1.0,
    "action_rate": 0.00843,
    "jerk": 0.00555,
    "hf_ratio": 0.15876,
    "achieved_vx_mean": -2e-05,
    "achieved_vy_mean": -3e-05,
    "achieved_wz_mean": -0.00017,
    "vx_err_mean": -0.10002,
    "vy_err_mean": -3e-05,
    "wz_err_mean": -0.00017,
    "vx_tracking_score": 0.01828,
    "vy_tracking_score": 1.0,
    "wz_tracking_score": 1.0,
    "net_speed_x": -2e-05,
    "net_speed_y": -3e-05,
    "total_distance": 0.09814,
    "orientation_cost": 0.00369,
    "max_tilt_deg": 3.92494,
    "mean_tilt_deg": 3.47148,
    "base_height_mean": 0.15702,
    "base_height_std": 0.00056,
    "left_swing_peak": 0.00269,
    "right_swing_peak": 0.00305,
    "mean_swing_peak": 0.00287,
    "left_step_count": 1.5,
    "right_step_count": 1.0,
    "step_frequency_hz": 0.125,
    "air_time_ratio": 0.0015,
    "double_support_ratio": 0.9985,
    "left_air_ratio": 0.0015,
    "right_air_ratio": 0.001,
    "step_count_symmetry": 0.75,
    "air_time_symmetry": 0.74938,
    "swing_peak_symmetry": 0.87768,
    "gait_symmetry_score": 0.79235
  },
  "backward_walk": {
    "steps": 1000.0,
    "survival_rate": 1.0,
    "action_rate": 0.00919,
    "jerk": 0.00866,
    "hf_ratio": 0.26875,
    "achieved_vx_mean": 2e-05,
    "achieved_vy_mean": -4e-05,
    "achieved_wz_mean": 7e-05,
    "vx_err_mean": 0.10002,
    "vy_err_mean": -4e-05,
    "wz_err_mean": 7e-05,
    "vx_tracking_score": 0.01828,
    "vy_tracking_score": 1.0,
    "wz_tracking_score": 1.0,
    "net_speed_x": 2e-05,
    "net_speed_y": -3e-05,
    "total_distance": 0.06455,
    "orientation_cost": 0.00509,
    "max_tilt_deg": 5.3658,
    "mean_tilt_deg": 4.08092,
    "base_height_mean": 0.15597,
    "base_height_std": 0.00053,
    "left_swing_peak": 0.0023,
    "right_swing_peak": 0.00434,
    "mean_swing_peak": 0.00332,
    "left_step_count": 1.0,
    "right_step_count": 1.0,
    "step_frequency_hz": 0.1,
    "air_time_ratio": 0.002,
    "double_support_ratio": 0.998,
    "left_air_ratio": 0.001,
    "right_air_ratio": 0.002,
    "step_count_symmetry": 1.0,
    "air_time_symmetry": 0.66611,
    "swing_peak_symmetry": 0.54338,
    "gait_symmetry_score": 0.7365
  },
  "lateral_left": {
    "steps": 1000.0,
    "survival_rate": 1.0,
    "action_rate": 0.01875,
    "jerk": 0.01194,
    "hf_ratio": 0.23694,
    "achieved_vx_mean": -0.00013,
    "achieved_vy_mean": -0.00029,
    "achieved_wz_mean": -0.00013,
    "vx_err_mean": -0.00013,
    "vy_err_mean": -0.15029,
    "wz_err_mean": -0.00013,
    "vx_tracking_score": 0.99999,
    "vy_tracking_score": 0.00012,
    "wz_tracking_score": 1.0,
    "net_speed_x": -9e-05,
    "net_speed_y": -0.00017,
    "total_distance": 0.31889,
    "orientation_cost": 0.00216,
    "max_tilt_deg": 4.36905,
    "mean_tilt_deg": 2.62741,
    "base_height_mean": 0.16113,
    "base_height_std": 0.00173,
    "left_swing_peak": 0.00161,
    "right_swing_peak": 0.0036,
    "mean_swing_peak": 0.00261,
    "left_step_count": 0.5,
    "right_step_count": 1.0,
    "step_frequency_hz": 0.075,
    "air_time_ratio": 0.002,
    "double_support_ratio": 0.998,
    "left_air_ratio": 0.001,
    "right_air_ratio": 0.001,
    "step_count_symmetry": 0.5,
    "air_time_symmetry": 0.24988,
    "swing_peak_symmetry": 0.4334,
    "gait_symmetry_score": 0.39443
  },
  "lateral_right": {
    "steps": 1000.0,
    "survival_rate": 1.0,
    "action_rate": 0.01064,
    "jerk": 0.00685,
    "hf_ratio": 0.15207,
    "achieved_vx_mean": 0.0,
    "achieved_vy_mean": -1e-05,
    "achieved_wz_mean": -0.00015,
    "vx_err_mean": 0.0,
    "vy_err_mean": 0.14999,
    "wz_err_mean": -0.00015,
    "vx_tracking_score": 1.0,
    "vy_tracking_score": 0.00012,
    "wz_tracking_score": 1.0,
    "net_speed_x": -0.0,
    "net_speed_y": -3e-05,
    "total_distance": 0.13105,
    "orientation_cost": 0.00402,
    "max_tilt_deg": 4.08451,
    "mean_tilt_deg": 3.61191,
    "base_height_mean": 0.15633,
    "base_height_std": 0.00041,
    "left_swing_peak": 0.0034,
    "right_swing_peak": 0.00456,
    "mean_swing_peak": 0.00398,
    "left_step_count": 1.5,
    "right_step_count": 1.0,
    "step_frequency_hz": 0.125,
    "air_time_ratio": 0.002,
    "double_support_ratio": 0.998,
    "left_air_ratio": 0.0015,
    "right_air_ratio": 0.0015,
    "step_count_symmetry": 0.75,
    "air_time_symmetry": 0.99925,
    "swing_peak_symmetry": 0.72856,
    "gait_symmetry_score": 0.82594
  },
  "turn_left": {
    "steps": 1000.0,
    "survival_rate": 1.0,
    "action_rate": 0.06312,
    "jerk": 0.04949,
    "hf_ratio": 0.21721,
    "achieved_vx_mean": 0.07213,
    "achieved_vy_mean": 0.0423,
    "achieved_wz_mean": 0.73094,
    "vx_err_mean": 0.07213,
    "vy_err_mean": 0.0423,
    "wz_err_mean": -0.06906,
    "vx_tracking_score": 0.12478,
    "vy_tracking_score": 0.48886,
    "wz_tracking_score": 0.8876,
    "net_speed_x": -0.00255,
    "net_speed_y": 0.00316,
    "total_distance": 2.64832,
    "orientation_cost": 0.00481,
    "max_tilt_deg": 6.46533,
    "mean_tilt_deg": 3.45038,
    "base_height_mean": 0.16001,
    "base_height_std": 0.00408,
    "left_swing_peak": 0.0038,
    "right_swing_peak": 0.02546,
    "mean_swing_peak": 0.01463,
    "left_step_count": 7.0,
    "right_step_count": 36.0,
    "step_frequency_hz": 2.15,
    "air_time_ratio": 0.319,
    "double_support_ratio": 0.681,
    "left_air_ratio": 0.007,
    "right_air_ratio": 0.312,
    "step_count_symmetry": 0.19444,
    "air_time_symmetry": 0.02243,
    "swing_peak_symmetry": 0.14938,
    "gait_symmetry_score": 0.12208
  },
  "turn_right": {
    "steps": 1000.0,
    "survival_rate": 1.0,
    "action_rate": 0.06839,
    "jerk": 0.05831,
    "hf_ratio": 0.2247,
    "achieved_vx_mean": 0.03363,
    "achieved_vy_mean": -0.08378,
    "achieved_wz_mean": -0.81831,
    "vx_err_mean": 0.03363,
    "vy_err_mean": -0.08378,
    "wz_err_mean": -0.01831,
    "vx_tracking_score": 0.63617,
    "vy_tracking_score": 0.06034,
    "wz_tracking_score": 0.99159,
    "net_speed_x": -0.00877,
    "net_speed_y": 0.00646,
    "total_distance": 2.26918,
    "orientation_cost": 0.00367,
    "max_tilt_deg": 6.6631,
    "mean_tilt_deg": 3.10758,
    "base_height_mean": 0.15737,
    "base_height_std": 0.00213,
    "left_swing_peak": 0.0233,
    "right_swing_peak": 0.00631,
    "mean_swing_peak": 0.0148,
    "left_step_count": 43.0,
    "right_step_count": 38.0,
    "step_frequency_hz": 4.05,
    "air_time_ratio": 0.4585,
    "double_support_ratio": 0.5415,
    "left_air_ratio": 0.3005,
    "right_air_ratio": 0.162,
    "step_count_symmetry": 0.88372,
    "air_time_symmetry": 0.53916,
    "swing_peak_symmetry": 0.27101,
    "gait_symmetry_score": 0.56463
  },
  "fwd_strafe_left": {
    "steps": 1000.0,
    "survival_rate": 1.0,
    "action_rate": 0.02932,
    "jerk": 0.01669,
    "hf_ratio": 0.13299,
    "achieved_vx_mean": -0.00011,
    "achieved_vy_mean": -0.0023,
    "achieved_wz_mean": -0.00376,
    "vx_err_mean": -0.10011,
    "vy_err_mean": -0.1523,
    "wz_err_mean": -0.00376,
    "vx_tracking_score": 0.01815,
    "vy_tracking_score": 9e-05,
    "wz_tracking_score": 0.99965,
    "net_speed_x": 0.00021,
    "net_speed_y": -0.00229,
    "total_distance": 0.58596,
    "orientation_cost": 0.00199,
    "max_tilt_deg": 3.25124,
    "mean_tilt_deg": 2.53459,
    "base_height_mean": 0.16423,
    "base_height_std": 0.00293,
    "left_swing_peak": 0.00467,
    "right_swing_peak": 0.0,
    "mean_swing_peak": 0.00233,
    "left_step_count": 6.0,
    "right_step_count": 0.0,
    "step_frequency_hz": 0.3,
    "air_time_ratio": 0.006,
    "double_support_ratio": 0.994,
    "left_air_ratio": 0.006,
    "right_air_ratio": 0.0,
    "step_count_symmetry": 0.0,
    "air_time_symmetry": 0.0,
    "swing_peak_symmetry": 0.0,
    "gait_symmetry_score": 0.0
  },
  "fwd_strafe_right": {
    "steps": 1000.0,
    "survival_rate": 1.0,
    "action_rate": 0.02097,
    "jerk": 0.0127,
    "hf_ratio": 0.14892,
    "achieved_vx_mean": -3e-05,
    "achieved_vy_mean": 0.00017,
    "achieved_wz_mean": -0.00031,
    "vx_err_mean": -0.10003,
    "vy_err_mean": 0.15017,
    "wz_err_mean": -0.00031,
    "vx_tracking_score": 0.01828,
    "vy_tracking_score": 0.00012,
    "wz_tracking_score": 1.0,
    "net_speed_x": -1e-05,
    "net_speed_y": 4e-05,
    "total_distance": 0.37765,
    "orientation_cost": 0.00248,
    "max_tilt_deg": 3.80039,
    "mean_tilt_deg": 2.73914,
    "base_height_mean": 0.15798,
    "base_height_std": 0.00168,
    "left_swing_peak": 0.00394,
    "right_swing_peak": 0.00618,
    "mean_swing_peak": 0.00506,
    "left_step_count": 1.0,
    "right_step_count": 1.0,
    "step_frequency_hz": 0.1,
    "air_time_ratio": 0.007,
    "double_support_ratio": 0.993,
    "left_air_ratio": 0.003,
    "right_air_ratio": 0.004,
    "step_count_symmetry": 1.0,
    "air_time_symmetry": 0.74981,
    "swing_peak_symmetry": 0.63688,
    "gait_symmetry_score": 0.79556
  },
  "fwd_turn_left": {
    "steps": 1000.0,
    "survival_rate": 1.0,
    "action_rate": 0.06339,
    "jerk": 0.05074,
    "hf_ratio": 0.21689,
    "achieved_vx_mean": 0.07662,
    "achieved_vy_mean": 0.04302,
    "achieved_wz_mean": 0.73055,
    "vx_err_mean": -0.02338,
    "vy_err_mean": 0.04302,
    "wz_err_mean": -0.06945,
    "vx_tracking_score": 0.80362,
    "vy_tracking_score": 0.47703,
    "wz_tracking_score": 0.88638,
    "net_speed_x": -0.00298,
    "net_speed_y": 0.00369,
    "total_distance": 2.56727,
    "orientation_cost": 0.00602,
    "max_tilt_deg": 7.45227,
    "mean_tilt_deg": 3.97549,
    "base_height_mean": 0.1588,
    "base_height_std": 0.00377,
    "left_swing_peak": 0.00314,
    "right_swing_peak": 0.02391,
    "mean_swing_peak": 0.01352,
    "left_step_count": 16.5,
    "right_step_count": 36.0,
    "step_frequency_hz": 2.625,
    "air_time_ratio": 0.3145,
    "double_support_ratio": 0.6855,
    "left_air_ratio": 0.0195,
    "right_air_ratio": 0.295,
    "step_count_symmetry": 0.45833,
    "air_time_symmetry": 0.0661,
    "swing_peak_symmetry": 0.13124,
    "gait_symmetry_score": 0.21856
  },
  "fwd_turn_right": {
    "steps": 1000.0,
    "survival_rate": 1.0,
    "action_rate": 0.07062,
    "jerk": 0.05734,
    "hf_ratio": 0.2134,
    "achieved_vx_mean": 0.07223,
    "achieved_vy_mean": -0.05594,
    "achieved_wz_mean": -0.84657,
    "vx_err_mean": -0.02777,
    "vy_err_mean": -0.05594,
    "wz_err_mean": -0.04657,
    "vx_tracking_score": 0.73458,
    "vy_tracking_score": 0.286,
    "wz_tracking_score": 0.94722,
    "net_speed_x": -0.01133,
    "net_speed_y": 0.0049,
    "total_distance": 2.55591,
    "orientation_cost": 0.00622,
    "max_tilt_deg": 7.50503,
    "mean_tilt_deg": 4.23253,
    "base_height_mean": 0.15907,
    "base_height_std": 0.00278,
    "left_swing_peak": 0.02775,
    "right_swing_peak": 0.00501,
    "mean_swing_peak": 0.01638,
    "left_step_count": 46.5,
    "right_step_count": 61.5,
    "step_frequency_hz": 5.4,
    "air_time_ratio": 0.41,
    "double_support_ratio": 0.59,
    "left_air_ratio": 0.33,
    "right_air_ratio": 0.082,
    "step_count_symmetry": 0.75768,
    "air_time_symmetry": 0.24848,
    "swing_peak_symmetry": 0.18044,
    "gait_symmetry_score": 0.39554
  },
  "back_turn_left": {
    "steps": 1000.0,
    "survival_rate": 1.0,
    "action_rate": 0.05885,
    "jerk": 0.04395,
    "hf_ratio": 0.19515,
    "achieved_vx_mean": 0.07055,
    "achieved_vy_mean": 0.04406,
    "achieved_wz_mean": 0.78799,
    "vx_err_mean": 0.17055,
    "vy_err_mean": 0.04406,
    "wz_err_mean": -0.01201,
    "vx_tracking_score": 1e-05,
    "vy_tracking_score": 0.45999,
    "wz_tracking_score": 0.9964,
    "net_speed_x": -0.00854,
    "net_speed_y": 0.00125,
    "total_distance": 2.74314,
    "orientation_cost": 0.0053,
    "max_tilt_deg": 7.00487,
    "mean_tilt_deg": 3.691,
    "base_height_mean": 0.16126,
    "base_height_std": 0.00383,
    "left_swing_peak": 0.0046,
    "right_swing_peak": 0.02856,
    "mean_swing_peak": 0.01658,
    "left_step_count": 15.5,
    "right_step_count": 47.5,
    "step_frequency_hz": 3.15,
    "air_time_ratio": 0.3705,
    "double_support_ratio": 0.6295,
    "left_air_ratio": 0.0175,
    "right_air_ratio": 0.3535,
    "step_count_symmetry": 0.32564,
    "air_time_symmetry": 0.04949,
    "swing_peak_symmetry": 0.16113,
    "gait_symmetry_score": 0.17875
  },
  "back_turn_right": {
    "steps": 1000.0,
    "survival_rate": 1.0,
    "action_rate": 0.06838,
    "jerk": 0.06183,
    "hf_ratio": 0.2335,
    "achieved_vx_mean": 0.00867,
    "achieved_vy_mean": -0.08822,
    "achieved_wz_mean": -0.74298,
    "vx_err_mean": 0.10867,
    "vy_err_mean": -0.08822,
    "wz_err_mean": 0.05702,
    "vx_tracking_score": 0.00888,
    "vy_tracking_score": 0.04448,
    "wz_tracking_score": 0.92192,
    "net_speed_x": -0.0047,
    "net_speed_y": 0.00071,
    "total_distance": 2.23816,
    "orientation_cost": 0.00348,
    "max_tilt_deg": 5.49244,
    "mean_tilt_deg": 3.08315,
    "base_height_mean": 0.15566,
    "base_height_std": 0.0024,
    "left_swing_peak": 0.02068,
    "right_swing_peak": 0.00696,
    "mean_swing_peak": 0.01382,
    "left_step_count": 41.5,
    "right_step_count": 38.0,
    "step_frequency_hz": 3.975,
    "air_time_ratio": 0.4865,
    "double_support_ratio": 0.5135,
    "left_air_ratio": 0.3035,
    "right_air_ratio": 0.184,
    "step_count_symmetry": 0.91599,
    "air_time_symmetry": 0.60626,
    "swing_peak_symmetry": 0.33649,
    "gait_symmetry_score": 0.61958
  },
  "standing": {
    "steps": 1000.0,
    "survival_rate": 1.0,
    "action_rate": 0.00844,
    "jerk": 0.00681,
    "hf_ratio": 0.2439,
    "achieved_vx_mean": 1e-05,
    "achieved_vy_mean": -7e-05,
    "achieved_wz_mean": -9e-05,
    "vx_err_mean": 1e-05,
    "vy_err_mean": -7e-05,
    "wz_err_mean": -9e-05,
    "vx_tracking_score": 1.0,
    "vy_tracking_score": 1.0,
    "wz_tracking_score": 1.0,
    "net_speed_x": 1e-05,
    "net_speed_y": -6e-05,
    "total_distance": 0.11243,
    "orientation_cost": 0.00984,
    "max_tilt_deg": 5.85068,
    "mean_tilt_deg": 5.67116,
    "base_height_mean": 0.15361,
    "base_height_std": 0.00068,
    "left_swing_peak": 0.00533,
    "right_swing_peak": 0.00573,
    "mean_swing_peak": 0.00553,
    "left_step_count": 1.5,
    "right_step_count": 1.0,
    "step_frequency_hz": 0.125,
    "air_time_ratio": 0.006,
    "double_support_ratio": 0.994,
    "left_air_ratio": 0.0035,
    "right_air_ratio": 0.003,
    "step_count_symmetry": 0.75,
    "air_time_symmetry": 0.87474,
    "swing_peak_symmetry": 0.78362,
    "gait_symmetry_score": 0.80279
  },
  "push_recovery": {
    "push_0.3_front": {
      "survival_rate": 1.0,
      "max_tilt_after_push_deg": 5.4
    },
    "push_0.3_back": {
      "survival_rate": 1.0,
      "max_tilt_after_push_deg": 5.3
    },
    "push_0.3_side": {
      "survival_rate": 1.0,
      "max_tilt_after_push_deg": 5.3
    },
    "push_0.6_front": {
      "survival_rate": 0.0,
      "max_tilt_after_push_deg": 90.0
    },
    "push_0.6_back": {
      "survival_rate": 0.0,
      "max_tilt_after_push_deg": 90.0
    },
    "push_0.6_side": {
      "survival_rate": 1.0,
      "max_tilt_after_push_deg": 5.3
    },
    "push_1.0_front": {
      "survival_rate": 0.0,
      "max_tilt_after_push_deg": 90.0
    },
    "push_1.0_back": {
      "survival_rate": 0.0,
      "max_tilt_after_push_deg": 90.0
    },
    "push_1.0_side": {
      "survival_rate": 1.0,
      "max_tilt_after_push_deg": 5.3
    },
    "push_1.5_front": {
      "survival_rate": 0.0,
      "max_tilt_after_push_deg": 90.0
    },
    "push_1.5_back": {
      "survival_rate": 0.0,
      "max_tilt_after_push_deg": 90.0
    },
    "push_1.5_side": {
      "survival_rate": 0.0,
      "max_tilt_after_push_deg": 90.0
    }
  },
  "responsiveness": {
    "stand_then_forward": {
      "vx": -4e-05,
      "vy": 2e-05,
      "wz": 0.00026,
      "vx_score": 0.018,
      "vy_score": 1.0,
      "wz_score": 1.0,
      "vx_early": -4e-05,
      "vx_steady": -9e-05,
      "vy_early": 0.00014,
      "vy_steady": -0.00014,
      "wz_early": 0.00102,
      "wz_steady": 0.00017,
      "time_to_vx_steps": null,
      "time_to_vy_steps": null,
      "time_to_wz_steps": null,
      "duration_steps": 780
    },
    "stand_then_backward": {
      "vx": -3e-05,
      "vy": 2e-05,
      "wz": 0.00023,
      "vx_score": 0.018,
      "vy_score": 1.0,
      "wz_score": 1.0,
      "vx_early": -0.00011,
      "vx_steady": -3e-05,
      "vy_early": 0.00016,
      "vy_steady": -8e-05,
      "wz_early": 0.00031,
      "wz_steady": 0.00014,
      "time_to_vx_steps": null,
      "time_to_vy_steps": null,
      "time_to_wz_steps": null,
      "duration_steps": 780
    },
    "stand_then_strafe_left": {
      "vx": -7e-05,
      "vy": -0.00024,
      "wz": 0.00029,
      "vx_score": 1.0,
      "vy_score": 0.0,
      "wz_score": 1.0,
      "vx_early": 0.0002,
      "vx_steady": -0.00013,
      "vy_early": 3e-05,
      "vy_steady": -0.00042,
      "wz_early": 0.00097,
      "wz_steady": -0.00022,
      "time_to_vx_steps": null,
      "time_to_vy_steps": null,
      "time_to_wz_steps": null,
      "duration_steps": 780
    },
    "stand_then_strafe_right": {
      "vx": -1e-05,
      "vy": -1e-05,
      "wz": -0.00029,
      "vx_score": 1.0,
      "vy_score": 0.0,
      "wz_score": 1.0,
      "vx_early": -4e-05,
      "vx_steady": -0.00015,
      "vy_early": 3e-05,
      "vy_steady": -7e-05,
      "wz_early": -0.00029,
      "wz_steady": -0.00066,
      "time_to_vx_steps": null,
      "time_to_vy_steps": null,
      "time_to_wz_steps": null,
      "duration_steps": 780
    },
    "stand_then_turn_left": {
      "vx": 0.0722,
      "vy": 0.04324,
      "wz": 0.72986,
      "vx_score": 0.124,
      "vy_score": 0.473,
      "wz_score": 0.884,
      "vx_early": 0.07297,
      "vx_steady": 0.07348,
      "vy_early": 0.04664,
      "vy_steady": 0.04515,
      "wz_early": 0.73125,
      "wz_steady": 0.7296,
      "time_to_vx_steps": null,
      "time_to_vy_steps": null,
      "time_to_wz_steps": 0,
      "duration_steps": 780
    },
    "stand_then_turn_right": {
      "vx": 0.03347,
      "vy": -0.08365,
      "wz": -0.81937,
      "vx_score": 0.639,
      "vy_score": 0.061,
      "wz_score": 0.991,
      "vx_early": 0.03438,
      "vx_steady": 0.03178,
      "vy_early": -0.08226,
      "vy_steady": -0.07967,
      "wz_early": -0.81214,
      "wz_steady": -0.81982,
      "time_to_vx_steps": null,
      "time_to_vy_steps": null,
      "time_to_wz_steps": 0,
      "duration_steps": 780
    },
    "stand_then_fwd_strafe_left": {
      "vx": 0.00028,
      "vy": -0.00232,
      "wz": -0.00295,
      "vx_score": 0.019,
      "vy_score": 0.0,
      "wz_score": 1.0,
      "vx_early": 0.00148,
      "vx_steady": -0.00013,
      "vy_early": -0.00211,
      "vy_steady": -0.00248,
      "wz_early": -0.00324,
      "wz_steady": -0.00231,
      "time_to_vx_steps": 13,
      "time_to_vy_steps": null,
      "time_to_wz_steps": null,
      "duration_steps": 780
    },
    "stand_then_fwd_strafe_right": {
      "vx": -0.00012,
      "vy": 0.00015,
      "wz": 0.00039,
      "vx_score": 0.018,
      "vy_score": 0.0,
      "wz_score": 1.0,
      "vx_early": -0.00038,
      "vx_steady": -0.00025,
      "vy_early": 5e-05,
      "vy_steady": 0.00049,
      "wz_early": 0.00221,
      "wz_steady": -0.00093,
      "time_to_vx_steps": null,
      "time_to_vy_steps": null,
      "time_to_wz_steps": null,
      "duration_steps": 780
    },
    "stand_then_fwd_turn_left": {
      "vx": 0.07678,
      "vy": 0.04402,
      "wz": 0.73476,
      "vx_score": 0.806,
      "vy_score": 0.461,
      "wz_score": 0.899,
      "vx_early": 0.07707,
      "vx_steady": 0.07847,
      "vy_early": 0.047,
      "vy_steady": 0.04559,
      "wz_early": 0.73516,
      "wz_steady": 0.73742,
      "time_to_vx_steps": 6,
      "time_to_vy_steps": null,
      "time_to_wz_steps": 0,
      "duration_steps": 780
    },
    "stand_then_fwd_turn_right": {
      "vx": 0.07225,
      "vy": -0.05565,
      "wz": -0.84122,
      "vx_score": 0.735,
      "vy_score": 0.29,
      "wz_score": 0.958,
      "vx_early": 0.07379,
      "vx_steady": 0.07001,
      "vy_early": -0.05278,
      "vy_steady": -0.0533,
      "wz_early": -0.83021,
      "wz_steady": -0.84491,
      "time_to_vx_steps": 0,
      "time_to_vy_steps": null,
      "time_to_wz_steps": 0,
      "duration_steps": 780
    },
    "stand_then_back_turn_left": {
      "vx": 0.07108,
      "vy": 0.04539,
      "wz": 0.7884,
      "vx_score": 0.0,
      "vy_score": 0.439,
      "wz_score": 0.997,
      "vx_early": 0.07226,
      "vx_steady": 0.07234,
      "vy_early": 0.04835,
      "vy_steady": 0.04769,
      "wz_early": 0.78487,
      "wz_steady": 0.78871,
      "time_to_vx_steps": null,
      "time_to_vy_steps": null,
      "time_to_wz_steps": 0,
      "duration_steps": 780
    },
    "stand_then_back_turn_right": {
      "vx": 0.00865,
      "vy": -0.08772,
      "wz": -0.74123,
      "vx_score": 0.009,
      "vy_score": 0.046,
      "wz_score": 0.917,
      "vx_early": 0.00944,
      "vx_steady": 0.00855,
      "vy_early": -0.08532,
      "vy_steady": -0.08586,
      "wz_early": -0.73169,
      "wz_steady": -0.74193,
      "time_to_vx_steps": null,
      "time_to_vy_steps": null,
      "time_to_wz_steps": 0,
      "duration_steps": 780
    },
    "stand_then_strafe_turn_left": {
      "vx": 0.07129,
      "vy": 0.05864,
      "wz": 0.79927,
      "vx_score": 0.131,
      "vy_score": 0.035,
      "wz_score": 1.0,
      "vx_early": 0.07231,
      "vx_steady": 0.07241,
      "vy_early": 0.06016,
      "vy_steady": 0.06131,
      "wz_early": 0.80236,
      "wz_steady": 0.79815,
      "time_to_vx_steps": null,
      "time_to_vy_steps": 8,
      "time_to_wz_steps": 1,
      "duration_steps": 780
    },
    "stand_then_strafe_turn_right": {
      "vx": 0.02505,
      "vy": -0.1342,
      "wz": -0.76431,
      "vx_score": 0.778,
      "vy_score": 0.905,
      "wz_score": 0.969,
      "vx_early": 0.02498,
      "vx_steady": 0.02378,
      "vy_early": -0.1352,
      "vy_steady": -0.12867,
      "wz_early": -0.75955,
      "wz_steady": -0.76618,
      "time_to_vx_steps": null,
      "time_to_vy_steps": 0,
      "time_to_wz_steps": 0,
      "duration_steps": 780
    }
  },
  "command_gating": {
    "strafe_persists_without_turn_left": {
      "with_turn": {
        "vx": 0.0698,
        "vy": 0.05278,
        "wz": 0.78964,
        "vx_score": 0.142,
        "vy_score": 0.023,
        "wz_score": 0.997,
        "vx_early": 0.07405,
        "vx_steady": 0.0639,
        "vy_early": 0.05787,
        "vy_steady": 0.05704,
        "wz_early": 0.77262,
        "wz_steady": 0.78395,
        "time_to_vx_steps": null,
        "time_to_vy_steps": 0,
        "time_to_wz_steps": 0,
        "duration_steps": 180
      },
      "turn_removed": {
        "vx": 0.00013,
        "vy": -0.00044,
        "wz": -0.0031,
        "vx_score": 1.0,
        "vy_score": 0.0,
        "wz_score": 1.0,
        "vx_early": 0.00055,
        "vx_steady": 0.00018,
        "vy_early": -0.00097,
        "vy_steady": -0.00046,
        "wz_early": -0.00894,
        "wz_steady": -0.00149,
        "time_to_vx_steps": null,
        "time_to_vy_steps": null,
        "time_to_wz_steps": null,
        "duration_steps": 280
      }
    },
    "strafe_persists_without_turn_right": {
      "with_turn": {
        "vx": 0.0254,
        "vy": -0.13916,
        "wz": -0.76622,
        "vx_score": 0.772,
        "vy_score": 0.954,
        "wz_score": 0.972,
        "vx_early": 0.02806,
        "vx_steady": 0.0259,
        "vy_early": -0.12118,
        "vy_steady": -0.14391,
        "wz_early": -0.77488,
        "wz_steady": -0.76491,
        "time_to_vx_steps": null,
        "time_to_vy_steps": 5,
        "time_to_wz_steps": 0,
        "duration_steps": 180
      },
      "turn_removed": {
        "vx": 2e-05,
        "vy": -0.00011,
        "wz": -0.00507,
        "vx_score": 1.0,
        "vy_score": 0.0,
        "wz_score": 0.999,
        "vx_early": 0.0001,
        "vx_steady": 0.00023,
        "vy_early": -0.00064,
        "vy_steady": 0.00029,
        "wz_early": -0.01611,
        "wz_steady": 0.00208,
        "time_to_vx_steps": null,
        "time_to_vy_steps": null,
        "time_to_wz_steps": null,
        "duration_steps": 280
      }
    },
    "strafe_persists_without_forward": {
      "with_forward": {
        "vx": -5e-05,
        "vy": -0.00281,
        "wz": -0.00111,
        "vx_score": 0.018,
        "vy_score": 0.0,
        "wz_score": 1.0,
        "vx_early": -0.00019,
        "vx_steady": 0.00048,
        "vy_early": -0.0028,
        "vy_steady": -0.00151,
        "wz_early": 0.01375,
        "wz_steady": -0.00474,
        "time_to_vx_steps": null,
        "time_to_vy_steps": null,
        "time_to_wz_steps": null,
        "duration_steps": 180
      },
      "forward_removed": {
        "vx": 6e-05,
        "vy": -0.00061,
        "wz": -0.00318,
        "vx_score": 1.0,
        "vy_score": 0.0,
        "wz_score": 1.0,
        "vx_early": 0.00032,
        "vx_steady": 0.00019,
        "vy_early": -0.00148,
        "vy_steady": -0.00047,
        "wz_early": -0.0092,
        "wz_steady": -0.00144,
        "time_to_vx_steps": null,
        "time_to_vy_steps": null,
        "time_to_wz_steps": null,
        "duration_steps": 280
      }
    }
  },
  "aggregate_locomotion": {
    "action_rate": 0.04084,
    "jerk": 0.032,
    "hf_ratio": 0.19994,
    "orientation_cost": 0.00408,
    "mean_swing_peak": 0.00916,
    "step_frequency_hz": 1.84792,
    "vx_tracking_score": 0.36509,
    "vy_tracking_score": 0.3181,
    "wz_tracking_score": 0.96923,
    "survival_rate": 1.0,
    "mean_tilt_deg": 3.3838,
    "gait_symmetry_score": 0.47033,
    "step_count_symmetry": 0.62798
  },
  "responsiveness_aggregate": {
    "stand_then_forward_score": 0.018,
    "stand_then_backward_score": 0.018,
    "stand_then_strafe_left_score": 0.0,
    "stand_then_strafe_right_score": 0.0,
    "stand_then_turn_left_score": 0.884,
    "stand_then_turn_right_score": 0.991,
    "stand_then_fwd_strafe_left_score": 0.009,
    "stand_then_fwd_strafe_right_score": 0.009,
    "stand_then_fwd_turn_left_score": 0.853,
    "stand_then_fwd_turn_right_score": 0.847,
    "stand_then_back_turn_left_score": 0.498,
    "stand_then_back_turn_right_score": 0.463,
    "stand_then_strafe_turn_left_score": 0.517,
    "stand_then_strafe_turn_right_score": 0.937,
    "mean_responsiveness": 0.4317
  },
  "metadata": {
    "onnx_path": "checkpoints/symmetric_extended/2026_05_14_021515_54067200.onnx",
    "num_episodes": 2,
    "evaluation_time_seconds": 12.8
  }
}